aifootprintcleaner/__init__.py
aifootprintcleaner/__main__.py
aifootprintcleaner/cleaner.py
aifootprintcleaner-0.1.1.dist-info/licenses/LICENSE
aifootprintcleaner-0.1.1.dist-info/METADATA
aifootprintcleaner-0.1.1.dist-info/WHEEL
aifootprintcleaner-0.1.1.dist-info/top_level.txt
aifootprintcleaner-0.1.1.dist-info/RECORD
